evautils/__init__.py
evautils/file_type/__init__.py
evautils/futures/__init__.py
evautils/requests/__init__.py
evautils-1.0.1.dist-info/LICENSE
evautils-1.0.1.dist-info/METADATA
evautils-1.0.1.dist-info/WHEEL
evautils-1.0.1.dist-info/top_level.txt
evautils-1.0.1.dist-info/RECORD
