Metadata-Version: 2.1
Name: evautils
Version: 1.0.1
Summary: Utils for Python.
Home-page: https://github.com/10e9928a/evautils
Author: shizhao
Author-email: shizhao@mail.nwpu.edu.cn
License: UNKNOWN
Platform: UNKNOWN
License-File: LICENSE
Requires-Dist: filetype
Requires-Dist: requests
